{
  "id": "prospect_1771976525839_j34kv1vg2",
  "businessName": "Plumbing Services by Able Plumbing",
  "phone": "(619) 985-8204",
  "email": null,
  "address": null,
  "city": "San Diego",
  "category": "Contractor",
  "website": "https://san-diego-plumbing.com/",
  "hasWebsite": true,
  "sourceUrl": "https://san-diego-plumbing.com/",
  "description": "Call or Text Us Now (619) 985-8204",
  "priority": 3,
  "scrapedAt": "2026-02-24T23:42:05.838Z",
  "stage": "Prospect Found",
  "status": "active",
  "createdAt": "2026-02-24T23:42:05.839Z",
  "updatedAt": "2026-02-24T23:42:05.839Z"
}